<?xml version="1.0" encoding="utf-8" ?>
<archive path="/people/achan/abcToA/jelloMold/jelloMold.abc" file_size="247755" last_updated="1437764329" app_name="Maya 2015 AbcExport v1.0" lib_version="Alembic 1.5.4 (built May  9 2014 14:09:51)" creation_time="Thu Jul 23 09:46:19 2015" description="Exported from: /work/19543_FUTURE/assets/character/shaderDev/look/jello_dev/shaderDev_jello_dev_002.ma" bounds="-63.5533,-0.140469,-63.5534,63.5533,47.7241,63.5533" start_time="0.042" end_time="0.042" has_velocity="0" constant="1">
    <xform constant="1" inherits_xform="1" matrix="1,0,0,0,0,1,0,0,0,0,1,0,0,0,0,1" name="geometry_GRP">
        <xform constant="1" inherits_xform="1" matrix="1,0,0,0,0,1,0,0,0,0,1,0,0,2.22045e-16,0,1" name="jello_REN">
            <poly_mesh constant="1" world_matrix="1,0,0,0,0,1,0,0,0,0,1,0,0,2.22045e-16,0,1" local_bounds="-52.765,0.560786,-53.9287,52.7649,47.7241,53.9286" world_bounds="-52.765,0.560786,-53.9287,52.7649,47.7241,53.9286" udims="1001" num_points="2018" num_faces="2016" num_vertices="8064" has_uvs="1" has_normals="1" overall_checksum="2425814825" point_checksum="2468551257" uv_checksum="4253827880" topology_checksum="586702335" name="jello_RENShape" />
        </xform>
        <xform constant="1" inherits_xform="1" matrix="1,0,0,0,0,1,0,0,0,0,1,0,0,0,0,1" name="plate_REN">
            <poly_mesh constant="1" world_matrix="1,0,0,0,0,1,0,0,0,0,1,0,0,0,0,1" local_bounds="-63.5533,-0.140469,-63.5534,63.5533,2.00221,63.5533" world_bounds="-63.5533,-0.140469,-63.5534,63.5533,2.00221,63.5533" udims="1001,1011" num_points="242" num_faces="260" num_vertices="1000" has_uvs="1" has_normals="1" overall_checksum="2812040690" point_checksum="3704266475" uv_checksum="1932069484" topology_checksum="853963606" name="plate_RENShape" />
        </xform>
    </xform>
</archive>
